tmb/__init__.py
tmb-0.1.5.dist-info/LICENSE
tmb-0.1.5.dist-info/METADATA
tmb-0.1.5.dist-info/WHEEL
tmb-0.1.5.dist-info/top_level.txt
tmb-0.1.5.dist-info/RECORD
