Metadata-Version: 2.1
Name: tmb
Version: 0.1.5
Summary: Library that interacts with TMB API
Home-page: https://github.com/alemuro/tmb
Author: alemuro
Author-email: hello@aleix.cloud
License: MIT
Keywords: tmb transports metropolitans barcelona tren metro bus
Platform: UNKNOWN
Classifier: Programming Language :: Python :: 3
Classifier: License :: OSI Approved :: MIT License
Classifier: Operating System :: OS Independent
Requires-Python: >=3.6
License-File: LICENSE
Requires-Dist: requests
